async_mariadb_connector/__init__.py
async_mariadb_connector/bulk.py
async_mariadb_connector/config.py
async_mariadb_connector/core.py
async_mariadb_connector/dataframe.py
async_mariadb_connector/exceptions.py
async_mariadb_connector-0.1.2.dist-info/licenses/LICENSE
async_mariadb_connector-0.1.2.dist-info/METADATA
async_mariadb_connector-0.1.2.dist-info/WHEEL
async_mariadb_connector-0.1.2.dist-info/top_level.txt
async_mariadb_connector-0.1.2.dist-info/RECORD
