Metadata-Version: 2.4
Name: async-mariadb-connector
Version: 0.1.2
Summary: A lightweight, production-grade, and asynchronous Python connector for MariaDB.
Author-email: Chanikya Nelapatla <chanikyac01@gmail.com>
License-Expression: MIT
Project-URL: Homepage, https://github.com/chanikkyasaai/async-mariadb-ml
Project-URL: Bug Tracker, https://github.com/chanikkyasaai/async-mariadb-ml/issues
Classifier: Development Status :: 4 - Beta
Classifier: Intended Audience :: Developers
Classifier: Operating System :: OS Independent
Classifier: Programming Language :: Python :: 3
Classifier: Programming Language :: Python :: 3.8
Classifier: Programming Language :: Python :: 3.9
Classifier: Programming Language :: Python :: 3.10
Classifier: Programming Language :: Python :: 3.11
Classifier: Topic :: Database
Classifier: Topic :: Software Development :: Libraries :: Python Modules
Requires-Python: >=3.8
License-File: LICENSE
Requires-Dist: aiomysql>=0.2.0
Requires-Dist: pandas>=2.0.0
Requires-Dist: python-dotenv>=1.0.0
Requires-Dist: tenacity>=8.2.3
Provides-Extra: dev
Requires-Dist: pytest>=8.0.0; extra == "dev"
Requires-Dist: pytest-asyncio>=0.21.0; extra == "dev"
Requires-Dist: pytest-cov>=4.0.0; extra == "dev"
Requires-Dist: faker>=20.0.0; extra == "dev"
Requires-Dist: langchain-core>=0.1.40; extra == "dev"
Requires-Dist: sentence-transformers>=2.2.2; extra == "dev"
Requires-Dist: numpy>=1.26.0; extra == "dev"
Requires-Dist: langsmith>=0.1.0; extra == "dev"
Requires-Dist: httpx>=0.25.0; extra == "dev"
Requires-Dist: unittest-xml-reporting>=3.2.0; extra == "dev"
Requires-Dist: tabulate>=0.9.0; extra == "dev"
Dynamic: license-file
